aws_transcription_grouper/__init__.py
aws_transcription_grouper/cli.py
aws_transcription_grouper/grouper.py
aws_transcription_grouper-0.1.2.dist-info/AUTHORS.rst
aws_transcription_grouper-0.1.2.dist-info/LICENSE
aws_transcription_grouper-0.1.2.dist-info/METADATA
aws_transcription_grouper-0.1.2.dist-info/WHEEL
aws_transcription_grouper-0.1.2.dist-info/entry_points.txt
aws_transcription_grouper-0.1.2.dist-info/top_level.txt
aws_transcription_grouper-0.1.2.dist-info/RECORD
