Metadata-Version: 2.1
Name: aws-transcription-grouper
Version: 0.1.2
Summary: CLI wrapper for transforming AWS Transcribe JSON files into txt files grouped by speaker.
Home-page: https://github.com/scuerda/aws_transcription_grouper
Author: Sasha Cuerda
Author-email: sasha.cuerda@gmail.com
License: MIT license
Keywords: aws_transcription_grouper
Platform: UNKNOWN
Classifier: Development Status :: 2 - Pre-Alpha
Classifier: Intended Audience :: Developers
Classifier: License :: OSI Approved :: MIT License
Classifier: Natural Language :: English
Classifier: Programming Language :: Python :: 3
Classifier: Programming Language :: Python :: 3.6
Classifier: Programming Language :: Python :: 3.7
Classifier: Programming Language :: Python :: 3.8
Requires-Python: >=3.6
License-File: LICENSE
License-File: AUTHORS.rst
Requires-Dist: tscribe
